kleenextractor
