Metadata-Version: 2.1
Name: KleenExtractor
Version: 0.1.2
Summary: Clean extract system to export folder content and sub content.
Home-page: UNKNOWN
Author: Edenskull
License: MIT
Platform: UNKNOWN
Classifier: Programming Language :: Python :: 3
Classifier: Programming Language :: Python :: 3.7
Classifier: Intended Audience :: Developers
Classifier: License :: OSI Approved :: MIT License
Classifier: Operating System :: OS Independent
